{
  "reddit": [
    {
      "subreddit": "TheRiseOfMyPower",
      "post": {
        "title": "{artworkTitle}, by me",
        "oc": true,
        "flairs": ["Artwork"]
      },
      "schedule": { "every": { "value": 1, "unit": "hour" } }
    },
    {
      "subreddit": "Art"
    },
    {
      "subreddit": "SpecArt"
    },
    {
      "subreddit": "drawing"
    },
    {
      "subreddit": "conceptart"
    },
    {
      "subreddit": "ArtBuddy"
    },
    {
      "subreddit": "IDAP"
    },
    {
      "subreddit": "Illustration"
    },
    {
      "subreddit": "pics"
    }
  ]
}
